{
    "name": "Evolution",
    "players": [
        {
            "username": "jxcvb",
            "score": 1507
        },
        {
            "username": "KingTrame",
            "score": 1146
        },
        {
            "username": "nfco",
            "score": 1049
        },
        {
            "username": "minerKC13",
            "score": 1035
        },
        {
            "username": "arizonagabe5",
            "score": 1023
        },
        {
            "username": "Dejectin",
            "score": 1010
        },
        {
            "username": "Blazespot",
            "score": 801
        },
        {
            "username": "2000YearsLater",
            "score": 791
        },
        {
            "username": "mab8400",
            "score": 674
        },
        {
            "username": "Hexxel3",
            "score": 670
        },
        {
            "username": "TheDeadlyGames",
            "score": 602
        },
        {
            "username": "_abiix_",
            "score": 600
        },
        {
            "username": "vezay",
            "score": 527
        },
        {
            "username": "SquadraCorse",
            "score": 516
        },
        {
            "username": "MASTS",
            "score": 511
        },
        {
            "username": "mathinoo",
            "score": 423
        },
        {
            "username": "Flamesie",
            "score": 404
        },
        {
            "username": "FranzLeopold",
            "score": 376
        },
        {
            "username": "JN_PlayzMC",
            "score": 361
        },
        {
            "username": "Kulminate",
            "score": 320
        },
        {
            "username": "Isabeeel",
            "score": 294
        },
        {
            "username": "mope_Dragon",
            "score": 291
        },
        {
            "username": "Vinny339",
            "score": 289
        },
        {
            "username": "Ery",
            "score": 285
        },
        {
            "username": "Uyanik",
            "score": 282
        },
        {
            "username": "Soul_Rack7659",
            "score": 272
        },
        {
            "username": "Majinnee",
            "score": 270
        },
        {
            "username": "twec",
            "score": 268
        },
        {
            "username": "OW6N",
            "score": 260
        },
        {
            "username": "cysk",
            "score": 258
        },
        {
            "username": "wrmf",
            "score": 255
        },
        {
            "username": "Thekidpplhate",
            "score": 254
        },
        {
            "username": "GangstaGoose",
            "score": 252
        },
        {
            "username": "laklek",
            "score": 242
        },
        {
            "username": "Cartix",
            "score": 239
        },
        {
            "username": "nwang888",
            "score": 238
        },
        {
            "username": "Sawga2",
            "score": 237
        },
        {
            "username": "Tomeroo",
            "score": 235
        },
        {
            "username": "Transpired",
            "score": 226
        },
        {
            "username": "dawrk",
            "score": 222
        },
        {
            "username": "Meeeezy",
            "score": 213
        },
        {
            "username": "OfflineTV",
            "score": 206
        },
        {
            "username": "oue",
            "score": 205
        },
        {
            "username": "MusicPokey101",
            "score": 200
        },
        {
            "username": "Zeyha_",
            "score": 199
        },
        {
            "username": "NeilThePenguin",
            "score": 198
        },
        {
            "username": "Jaek",
            "score": 197
        },
        {
            "username": "Binocular",
            "score": 196
        },
        {
            "username": "YouLostYourLife",
            "score": 192
        },
        {
            "username": "glaiveEnjoyer56",
            "score": 190
        },
        {
            "username": "lmaoluke",
            "score": 190
        },
        {
            "username": "Leqh",
            "score": 188
        },
        {
            "username": "JQE",
            "score": 188
        },
        {
            "username": "Sawga",
            "score": 187
        },
        {
            "username": "diceknot",
            "score": 186
        },
        {
            "username": "Milkycreampuff",
            "score": 183
        },
        {
            "username": "iamzario",
            "score": 180
        },
        {
            "username": "DWJosh",
            "score": 180
        },
        {
            "username": "BT21_RJ",
            "score": 179
        },
        {
            "username": "Abstractt",
            "score": 179
        },
        {
            "username": "Lilbair",
            "score": 176
        },
        {
            "username": "Skylord_G",
            "score": 176
        },
        {
            "username": "Cogsgoodbye",
            "score": 174
        },
        {
            "username": "Jumper1337__",
            "score": 172
        },
        {
            "username": "poke482fan",
            "score": 172
        },
        {
            "username": "TheNeonLazer",
            "score": 171
        },
        {
            "username": "karenlzrg",
            "score": 169
        },
        {
            "username": "iLone",
            "score": 169
        },
        {
            "username": "ThaumaturgX",
            "score": 165
        },
        {
            "username": "Kyce_Ignis",
            "score": 164
        },
        {
            "username": "_Woofie__",
            "score": 163
        },
        {
            "username": "IrocAce",
            "score": 163
        },
        {
            "username": "GoodNawBruh",
            "score": 162
        },
        {
            "username": "Chesschoco2513",
            "score": 161
        },
        {
            "username": "ChocolateDG2",
            "score": 161
        },
        {
            "username": "SameBeaches",
            "score": 161
        },
        {
            "username": "HowyaMate749",
            "score": 159
        },
        {
            "username": "cqsey",
            "score": 154
        },
        {
            "username": "Cohai",
            "score": 153
        },
        {
            "username": "Aviansie",
            "score": 153
        },
        {
            "username": "xXLiL_GupXx",
            "score": 152
        },
        {
            "username": "DecisiveWolf",
            "score": 150
        },
        {
            "username": "PS1",
            "score": 149
        },
        {
            "username": "LegoDan527",
            "score": 148
        },
        {
            "username": "henrikberg",
            "score": 147
        },
        {
            "username": "JKT115",
            "score": 146
        },
        {
            "username": "Villeh1",
            "score": 145
        },
        {
            "username": "ChasMasLivMas",
            "score": 144
        },
        {
            "username": "Defactorial",
            "score": 143
        },
        {
            "username": "DylAndrewBJ",
            "score": 142
        },
        {
            "username": "Crumplex",
            "score": 142
        },
        {
            "username": "JRCA",
            "score": 141
        },
        {
            "username": "Zurina",
            "score": 141
        },
        {
            "username": "Pilotkobra3",
            "score": 140
        },
        {
            "username": "Destinia",
            "score": 134
        },
        {
            "username": "LandmarkWings",
            "score": 133
        },
        {
            "username": "Limonzito21",
            "score": 133
        },
        {
            "username": "Hurrying",
            "score": 131
        },
        {
            "username": "coconutcowgirl",
            "score": 131
        },
        {
            "username": "emewy",
            "score": 131
        },
        {
            "username": "Notaker",
            "score": 130
        },
        {
            "username": "oStefan",
            "score": 129
        },
        {
            "username": "psgg",
            "score": 128
        },
        {
            "username": "wzpig",
            "score": 127
        },
        {
            "username": "FFig",
            "score": 127
        },
        {
            "username": "OXYGENOUS",
            "score": 126
        },
        {
            "username": "Roberto55",
            "score": 125
        },
        {
            "username": "MaitreDesBlocs",
            "score": 124
        },
        {
            "username": "combatively",
            "score": 123
        },
        {
            "username": "jacke1201",
            "score": 123
        },
        {
            "username": "DeCouto_05",
            "score": 123
        },
        {
            "username": "waitwhen",
            "score": 123
        },
        {
            "username": "Zenotick",
            "score": 122
        },
        {
            "username": "joshah",
            "score": 122
        },
        {
            "username": "Jeorge_",
            "score": 122
        },
        {
            "username": "Udaya",
            "score": 122
        },
        {
            "username": "BoxingWithBoxes",
            "score": 122
        },
        {
            "username": "iAteYourGrandma",
            "score": 121
        },
        {
            "username": "kevinsane",
            "score": 120
        },
        {
            "username": "LlamaNoLife",
            "score": 119
        },
        {
            "username": "fil",
            "score": 119
        },
        {
            "username": "xfeat",
            "score": 119
        },
        {
            "username": "Evgeen",
            "score": 119
        },
        {
            "username": "WAROF1RE",
            "score": 118
        },
        {
            "username": "Torrego",
            "score": 118
        },
        {
            "username": "Vincent008",
            "score": 118
        },
        {
            "username": "iLovePoptarts",
            "score": 118
        },
        {
            "username": "Slanyet",
            "score": 118
        },
        {
            "username": "ShyPegasus",
            "score": 117
        },
        {
            "username": "TheLoKeyLoki",
            "score": 115
        },
        {
            "username": "urmotherisahoe",
            "score": 115
        },
        {
            "username": "1000tepig",
            "score": 115
        },
        {
            "username": "Reckleton",
            "score": 114
        },
        {
            "username": "TheMouldyPotato",
            "score": 114
        },
        {
            "username": "_101_11",
            "score": 114
        },
        {
            "username": "scramps007",
            "score": 113
        },
        {
            "username": "lovelled",
            "score": 113
        },
        {
            "username": "Kale17",
            "score": 113
        },
        {
            "username": "oj990",
            "score": 113
        },
        {
            "username": "AdamxerPL",
            "score": 112
        },
        {
            "username": "kredster",
            "score": 112
        },
        {
            "username": "kuixincx",
            "score": 111
        },
        {
            "username": "ShowLlama",
            "score": 110
        },
        {
            "username": "DreamerSpring",
            "score": 110
        },
        {
            "username": "Baecn",
            "score": 110
        },
        {
            "username": "GotMemes",
            "score": 110
        },
        {
            "username": "Virant",
            "score": 108
        },
        {
            "username": "Knuckless_",
            "score": 107
        },
        {
            "username": "Ur_Grounded",
            "score": 107
        },
        {
            "username": "Dragnomist",
            "score": 106
        },
        {
            "username": "bcsb1001",
            "score": 106
        },
        {
            "username": "kkaybugga13",
            "score": 105
        },
        {
            "username": "Xukuwu",
            "score": 105
        },
        {
            "username": "Necrozmare",
            "score": 105
        },
        {
            "username": "Chloop",
            "score": 105
        },
        {
            "username": "Mat196",
            "score": 105
        },
        {
            "username": "xFearful",
            "score": 105
        },
        {
            "username": "Grego",
            "score": 105
        },
        {
            "username": "sharkea",
            "score": 104
        },
        {
            "username": "Kaiven",
            "score": 104
        },
        {
            "username": "LazyAdam_",
            "score": 103
        },
        {
            "username": "genegenegenegene",
            "score": 103
        },
        {
            "username": "UBUB",
            "score": 103
        },
        {
            "username": "evidentlyfresh",
            "score": 102
        },
        {
            "username": "nohwl",
            "score": 102
        },
        {
            "username": "durbLe",
            "score": 101
        },
        {
            "username": "LiviDk",
            "score": 101
        },
        {
            "username": "evanmoney",
            "score": 101
        },
        {
            "username": "maddi_nojams",
            "score": 100
        },
        {
            "username": "LIQHTNESS",
            "score": 100
        },
        {
            "username": "Z_E_R_A_T_H_I_X",
            "score": 100
        },
        {
            "username": "liqhts",
            "score": 100
        },
        {
            "username": "Luxely",
            "score": 100
        },
        {
            "username": "Craftings",
            "score": 100
        },
        {
            "username": "NNYL",
            "score": 99
        },
        {
            "username": "D_Stroyer5954",
            "score": 99
        },
        {
            "username": "CampusCreeper",
            "score": 98
        },
        {
            "username": "DGAMER47",
            "score": 97
        },
        {
            "username": "PTGPythoxYT1",
            "score": 97
        },
        {
            "username": "LukezPvP",
            "score": 97
        },
        {
            "username": "CinnSesame",
            "score": 97
        },
        {
            "username": "TrollSwagz",
            "score": 97
        },
        {
            "username": "Zythers",
            "score": 97
        },
        {
            "username": "pyite",
            "score": 97
        },
        {
            "username": "Awgmented",
            "score": 97
        },
        {
            "username": "Nyan0",
            "score": 96
        },
        {
            "username": "Miranda2202",
            "score": 95
        },
        {
            "username": "yanddere",
            "score": 94
        },
        {
            "username": "Rad1ance",
            "score": 94
        },
        {
            "username": "olympiio",
            "score": 94
        },
        {
            "username": "RareMemeDealer",
            "score": 94
        },
        {
            "username": "Cakebomb_",
            "score": 94
        },
        {
            "username": "Spacegod007",
            "score": 94
        },
        {
            "username": "Strider12",
            "score": 93
        },
        {
            "username": "FranzLeopold2",
            "score": 93
        },
        {
            "username": "Maseh",
            "score": 93
        },
        {
            "username": "Phock_Yuu",
            "score": 93
        },
        {
            "username": "KilledByVoid",
            "score": 93
        },
        {
            "username": "hexlotl",
            "score": 93
        },
        {
            "username": "rqil",
            "score": 93
        },
        {
            "username": "Miina1",
            "score": 92
        },
        {
            "username": "jewclient",
            "score": 91
        },
        {
            "username": "Cact",
            "score": 91
        },
        {
            "username": "Logstone",
            "score": 91
        },
        {
            "username": "annnq",
            "score": 90
        },
        {
            "username": "Fille510",
            "score": 90
        },
        {
            "username": "Lebigbertha",
            "score": 90
        },
        {
            "username": "StrawberryWookie",
            "score": 90
        },
        {
            "username": "Haxabur",
            "score": 90
        },
        {
            "username": "Recovs",
            "score": 90
        },
        {
            "username": "Osutogaroa",
            "score": 90
        },
        {
            "username": "creeperslayer637",
            "score": 90
        },
        {
            "username": "DaddyOnyankopon",
            "score": 90
        },
        {
            "username": "Klegger1412",
            "score": 90
        },
        {
            "username": "RandomGuy",
            "score": 90
        },
        {
            "username": "DiamondSplash",
            "score": 90
        },
        {
            "username": "TheLastThingUC",
            "score": 89
        },
        {
            "username": "KilledByBooks",
            "score": 88
        },
        {
            "username": "Tunfish",
            "score": 88
        },
        {
            "username": "Makiz",
            "score": 88
        },
        {
            "username": "SiCreations",
            "score": 88
        },
        {
            "username": "WAKO35",
            "score": 88
        },
        {
            "username": "MissElwing",
            "score": 88
        },
        {
            "username": "veer333",
            "score": 88
        },
        {
            "username": "nice_io",
            "score": 88
        },
        {
            "username": "poopie_girl",
            "score": 87
        },
        {
            "username": "Jerputti",
            "score": 87
        },
        {
            "username": "Galexsi",
            "score": 87
        },
        {
            "username": "ToxicPing",
            "score": 87
        },
        {
            "username": "daddiiiiii",
            "score": 86
        },
        {
            "username": "PiesAreLies",
            "score": 86
        },
        {
            "username": "gooosebumps",
            "score": 86
        },
        {
            "username": "Sethyy_Evalt",
            "score": 86
        },
        {
            "username": "fishtank33",
            "score": 86
        },
        {
            "username": "ups3t",
            "score": 85
        },
        {
            "username": "coolmatt746",
            "score": 85
        },
        {
            "username": "DylanDC14",
            "score": 85
        },
        {
            "username": "Lavq",
            "score": 85
        },
        {
            "username": "RatMite69",
            "score": 85
        },
        {
            "username": "XJuiraun",
            "score": 85
        },
        {
            "username": "wertia321",
            "score": 85
        },
        {
            "username": "jupitrr",
            "score": 84
        },
        {
            "username": "StarMatrix371",
            "score": 84
        },
        {
            "username": "Sartael",
            "score": 84
        },
        {
            "username": "Oyy",
            "score": 84
        },
        {
            "username": "xChqr",
            "score": 84
        },
        {
            "username": "xCxrson",
            "score": 84
        },
        {
            "username": "UltStream",
            "score": 84
        },
        {
            "username": "Darthz",
            "score": 83
        },
        {
            "username": "9erc",
            "score": 83
        },
        {
            "username": "AwwItsCookie",
            "score": 83
        },
        {
            "username": "BigsRichards",
            "score": 83
        },
        {
            "username": "Endorian",
            "score": 83
        },
        {
            "username": "ttfirebubbles",
            "score": 82
        },
        {
            "username": "Milomite",
            "score": 82
        },
        {
            "username": "nagicyan_desu",
            "score": 82
        },
        {
            "username": "McWolfiX",
            "score": 82
        },
        {
            "username": "sewper",
            "score": 82
        },
        {
            "username": "Jagdish",
            "score": 82
        },
        {
            "username": "PizzaMan319",
            "score": 82
        },
        {
            "username": "ThiccNoob",
            "score": 81
        },
        {
            "username": "Inferno9",
            "score": 81
        },
        {
            "username": "Closely",
            "score": 81
        },
        {
            "username": "ChromeBot",
            "score": 81
        },
        {
            "username": "Moist_Feet",
            "score": 81
        },
        {
            "username": "ignoring",
            "score": 81
        },
        {
            "username": "Monochromu",
            "score": 81
        },
        {
            "username": "MichaelGamer6",
            "score": 80
        },
        {
            "username": "xzelll",
            "score": 80
        },
        {
            "username": "Mysticate",
            "score": 80
        },
        {
            "username": "No_Malarkey",
            "score": 80
        },
        {
            "username": "NoHaxJustBaymax",
            "score": 80
        },
        {
            "username": "TurtleTamer",
            "score": 79
        },
        {
            "username": "lolitsloose",
            "score": 79
        },
        {
            "username": "astrophysi",
            "score": 79
        },
        {
            "username": "Gikoru_V2",
            "score": 79
        },
        {
            "username": "kellicat",
            "score": 79
        },
        {
            "username": "kscode911",
            "score": 79
        },
        {
            "username": "END_Natsu",
            "score": 79
        },
        {
            "username": "Scorious",
            "score": 79
        },
        {
            "username": "SHERRYMINECRAFT",
            "score": 78
        },
        {
            "username": "TEJT12",
            "score": 78
        },
        {
            "username": "Rian8337",
            "score": 78
        },
        {
            "username": "FlightOfIcarus",
            "score": 78
        },
        {
            "username": "One_Western_Boi",
            "score": 78
        },
        {
            "username": "iGoCrazy",
            "score": 77
        },
        {
            "username": "OSZCAR",
            "score": 77
        },
        {
            "username": "IlDuceZeroni",
            "score": 77
        },
        {
            "username": "cjbace",
            "score": 77
        },
        {
            "username": "Exameter",
            "score": 76
        },
        {
            "username": "bwubs",
            "score": 76
        },
        {
            "username": "Interstate29Stan",
            "score": 76
        },
        {
            "username": "nadjq",
            "score": 76
        },
        {
            "username": "ShinLim",
            "score": 75
        },
        {
            "username": "DUOSBIGGESTFAN",
            "score": 75
        },
        {
            "username": "Jusmat10",
            "score": 75
        },
        {
            "username": "PlayTimeIsOgre",
            "score": 75
        },
        {
            "username": "_SkyHawk_",
            "score": 75
        },
        {
            "username": "LordBukkit",
            "score": 75
        },
        {
            "username": "Allieee",
            "score": 75
        },
        {
            "username": "JacobRuby",
            "score": 75
        },
        {
            "username": "Dcnise",
            "score": 75
        },
        {
            "username": "Zerolized",
            "score": 75
        },
        {
            "username": "JayBird",
            "score": 75
        },
        {
            "username": "mcSpyTUC",
            "score": 74
        },
        {
            "username": "FluffCoated",
            "score": 74
        },
        {
            "username": "MilkFC",
            "score": 74
        },
        {
            "username": "Albax02",
            "score": 74
        },
        {
            "username": "Zafiu",
            "score": 74
        },
        {
            "username": "xWifey",
            "score": 74
        },
        {
            "username": "PacGoloB",
            "score": 74
        },
        {
            "username": "Foxariee",
            "score": 74
        },
        {
            "username": "Blinci",
            "score": 74
        },
        {
            "username": "Hqro",
            "score": 73
        },
        {
            "username": "taquiza",
            "score": 73
        },
        {
            "username": "Proper_Twelve",
            "score": 73
        },
        {
            "username": "CJPlayzYT",
            "score": 73
        },
        {
            "username": "imlynxy",
            "score": 73
        },
        {
            "username": "diemlan",
            "score": 73
        },
        {
            "username": "OfficialCutie",
            "score": 73
        },
        {
            "username": "fufill",
            "score": 73
        },
        {
            "username": "milkgrease",
            "score": 73
        },
        {
            "username": "Straix",
            "score": 73
        },
        {
            "username": "larrythellama2",
            "score": 72
        },
        {
            "username": "stefanohoho123",
            "score": 72
        },
        {
            "username": "Ayav",
            "score": 72
        },
        {
            "username": "biohazard31415",
            "score": 72
        },
        {
            "username": "MARKTHENUB",
            "score": 72
        },
        {
            "username": "Pabulous",
            "score": 72
        },
        {
            "username": "thealwaysseen",
            "score": 72
        },
        {
            "username": "Lunix",
            "score": 72
        },
        {
            "username": "Thegamerninja",
            "score": 72
        },
        {
            "username": "kittenOD",
            "score": 72
        },
        {
            "username": "Carocherus",
            "score": 72
        },
        {
            "username": "MissKaho",
            "score": 72
        },
        {
            "username": "CongruousJake",
            "score": 72
        },
        {
            "username": "T1KKA_",
            "score": 71
        },
        {
            "username": "DarkNight5725",
            "score": 71
        },
        {
            "username": "Furious_Lasers",
            "score": 71
        },
        {
            "username": "Toxidius",
            "score": 71
        },
        {
            "username": "sxniv",
            "score": 71
        },
        {
            "username": "Cutout",
            "score": 71
        },
        {
            "username": "WissTheMouss",
            "score": 71
        },
        {
            "username": "DIE_DIE_DIE_DIE",
            "score": 71
        },
        {
            "username": "KeynCat",
            "score": 71
        },
        {
            "username": "verlia",
            "score": 71
        },
        {
            "username": "slidforvon",
            "score": 71
        },
        {
            "username": "FactionsMason",
            "score": 70
        },
        {
            "username": "OleAAA",
            "score": 70
        },
        {
            "username": "Shubham",
            "score": 70
        },
        {
            "username": "Arimane",
            "score": 70
        },
        {
            "username": "frixzee",
            "score": 70
        },
        {
            "username": "Zruthe",
            "score": 70
        },
        {
            "username": "emofishermen",
            "score": 70
        },
        {
            "username": "Andrid02",
            "score": 69
        },
        {
            "username": "Da_Pr0Skilz_Peep",
            "score": 69
        },
        {
            "username": "zYualzu",
            "score": 69
        },
        {
            "username": "miscalled",
            "score": 69
        },
        {
            "username": "nimajneb3215",
            "score": 69
        },
        {
            "username": "Zuii",
            "score": 69
        },
        {
            "username": "jorrt",
            "score": 68
        },
        {
            "username": "savy03",
            "score": 68
        },
        {
            "username": "JDisaster",
            "score": 68
        },
        {
            "username": "onstandbi",
            "score": 68
        },
        {
            "username": "1Kokushibou",
            "score": 68
        },
        {
            "username": "69ms",
            "score": 68
        },
        {
            "username": "fiyu_",
            "score": 68
        },
        {
            "username": "ImParalyzed",
            "score": 68
        },
        {
            "username": "HWOHL",
            "score": 68
        },
        {
            "username": "HammerIonut2000",
            "score": 67
        },
        {
            "username": "neneposting",
            "score": 67
        },
        {
            "username": "Gustavotnt",
            "score": 67
        },
        {
            "username": "StrongFish2",
            "score": 67
        },
        {
            "username": "Itz_Adrian",
            "score": 67
        },
        {
            "username": "WORRYSTONE",
            "score": 67
        },
        {
            "username": "Sponkeh",
            "score": 67
        },
        {
            "username": "JoshuaAllenby",
            "score": 67
        },
        {
            "username": "HIDEONGOOSE",
            "score": 67
        },
        {
            "username": "fishjuice",
            "score": 67
        },
        {
            "username": "The_8_Bit_Zombie",
            "score": 67
        },
        {
            "username": "emmpathy",
            "score": 67
        },
        {
            "username": "ItzJuzt4Fun",
            "score": 67
        },
        {
            "username": "DiamondBull",
            "score": 66
        },
        {
            "username": "AyyZach",
            "score": 66
        },
        {
            "username": "HelenDS",
            "score": 66
        },
        {
            "username": "Necromanced",
            "score": 66
        },
        {
            "username": "bob_parker",
            "score": 66
        },
        {
            "username": "twistedcosmo",
            "score": 66
        },
        {
            "username": "tuttlenate",
            "score": 66
        },
        {
            "username": "BAS",
            "score": 66
        },
        {
            "username": "blubur",
            "score": 66
        },
        {
            "username": "Ocelotgod1",
            "score": 65
        },
        {
            "username": "skyman666",
            "score": 65
        },
        {
            "username": "FalseGuardian",
            "score": 65
        },
        {
            "username": "KawaiiQueenMerc",
            "score": 65
        },
        {
            "username": "Youtuberlz",
            "score": 65
        },
        {
            "username": "GamerAlbert",
            "score": 65
        },
        {
            "username": "_Mithy_",
            "score": 65
        },
        {
            "username": "Pixel_Cole",
            "score": 65
        },
        {
            "username": "EzS_DILWOLF",
            "score": 65
        },
        {
            "username": "Daudy",
            "score": 65
        },
        {
            "username": "skyref2002",
            "score": 64
        },
        {
            "username": "KnightDev",
            "score": 64
        },
        {
            "username": "Bikkie",
            "score": 64
        },
        {
            "username": "Torquezz",
            "score": 64
        },
        {
            "username": "Kcyi",
            "score": 64
        },
        {
            "username": "waterspout",
            "score": 64
        },
        {
            "username": "RainbowUnicornGM",
            "score": 64
        },
        {
            "username": "1_O",
            "score": 64
        },
        {
            "username": "Lucksu",
            "score": 64
        },
        {
            "username": "TheRunnerMaster",
            "score": 64
        },
        {
            "username": "qixelated",
            "score": 63
        },
        {
            "username": "Xtrm",
            "score": 63
        },
        {
            "username": "HeyItsAdam",
            "score": 63
        },
        {
            "username": "KaptainZoom",
            "score": 63
        },
        {
            "username": "LegendaryMiner93",
            "score": 63
        },
        {
            "username": "MrJaa",
            "score": 63
        },
        {
            "username": "Ashthulhu",
            "score": 63
        },
        {
            "username": "Fishywillow",
            "score": 63
        },
        {
            "username": "Randomlava34",
            "score": 63
        },
        {
            "username": "crazyadam516",
            "score": 63
        },
        {
            "username": "__KennyS__",
            "score": 63
        },
        {
            "username": "Climz",
            "score": 63
        },
        {
            "username": "germinomas",
            "score": 63
        },
        {
            "username": "NihonRiceSenpai",
            "score": 63
        },
        {
            "username": "SP3kTer_",
            "score": 62
        },
        {
            "username": "_Kanai_",
            "score": 62
        },
        {
            "username": "ApeMan1010",
            "score": 62
        },
        {
            "username": "MindOnYou",
            "score": 62
        },
        {
            "username": "Nxya",
            "score": 62
        },
        {
            "username": "sarahgamer812",
            "score": 62
        },
        {
            "username": "jcji",
            "score": 62
        },
        {
            "username": "LegionSole",
            "score": 62
        },
        {
            "username": "Lexotic",
            "score": 62
        },
        {
            "username": "MJ010101",
            "score": 62
        },
        {
            "username": "69kris",
            "score": 62
        },
        {
            "username": "thisIsWhoCares",
            "score": 62
        },
        {
            "username": "Hannugh",
            "score": 62
        },
        {
            "username": "iTest",
            "score": 62
        },
        {
            "username": "CoolGirl376",
            "score": 62
        },
        {
            "username": "RigBot",
            "score": 62
        },
        {
            "username": "L3VV15",
            "score": 62
        },
        {
            "username": "SteveFromSmashBr",
            "score": 62
        },
        {
            "username": "JCG",
            "score": 62
        },
        {
            "username": "pierdo",
            "score": 62
        },
        {
            "username": "Super_star_8",
            "score": 61
        },
        {
            "username": "queenav",
            "score": 61
        },
        {
            "username": "Planet_Clay",
            "score": 61
        },
        {
            "username": "eToast_",
            "score": 61
        },
        {
            "username": "HerboNapkin",
            "score": 61
        },
        {
            "username": "caycis",
            "score": 61
        },
        {
            "username": "Boringo123",
            "score": 61
        },
        {
            "username": "Hendrix98",
            "score": 61
        },
        {
            "username": "sillykid72",
            "score": 61
        },
        {
            "username": "Gallons",
            "score": 61
        },
        {
            "username": "Nexaulis",
            "score": 61
        },
        {
            "username": "MiningCreeper",
            "score": 61
        },
        {
            "username": "Snarlie",
            "score": 61
        },
        {
            "username": "Chameebling",
            "score": 61
        },
        {
            "username": "xokait",
            "score": 61
        },
        {
            "username": "BlueReallyGames",
            "score": 60
        },
        {
            "username": "Autumn_Myers",
            "score": 60
        },
        {
            "username": "TurnipPrices",
            "score": 60
        },
        {
            "username": "AvadaKedavra6",
            "score": 60
        },
        {
            "username": "Cookies4DayzM8",
            "score": 60
        },
        {
            "username": "Omnipitentic",
            "score": 60
        },
        {
            "username": "TrippyToad",
            "score": 60
        },
        {
            "username": "Cyndwen",
            "score": 60
        },
        {
            "username": "darkmoons1",
            "score": 60
        },
        {
            "username": "JohesL",
            "score": 60
        },
        {
            "username": "daKaizen",
            "score": 60
        },
        {
            "username": "Szey",
            "score": 60
        },
        {
            "username": "Chironsus",
            "score": 60
        },
        {
            "username": "Tree8602",
            "score": 60
        },
        {
            "username": "Colecvv",
            "score": 60
        },
        {
            "username": "clunker9",
            "score": 60
        },
        {
            "username": "fred5565",
            "score": 59
        },
        {
            "username": "impregnant69",
            "score": 59
        },
        {
            "username": "Jennly",
            "score": 59
        },
        {
            "username": "Pajojajo2002",
            "score": 59
        },
        {
            "username": "shlow",
            "score": 59
        },
        {
            "username": "dreamer101",
            "score": 59
        },
        {
            "username": "flame866",
            "score": 59
        },
        {
            "username": "KingDre",
            "score": 59
        },
        {
            "username": "Enntn",
            "score": 59
        },
        {
            "username": "SmokeArrow",
            "score": 59
        },
        {
            "username": "OfficialJeebus",
            "score": 59
        },
        {
            "username": "GoalCaufieldd",
            "score": 59
        },
        {
            "username": "JediMaik",
            "score": 59
        },
        {
            "username": "sterveey",
            "score": 59
        },
        {
            "username": "blushius",
            "score": 59
        },
        {
            "username": "1o2r3g",
            "score": 59
        },
        {
            "username": "Aschenbrenner",
            "score": 59
        },
        {
            "username": "craft_",
            "score": 59
        },
        {
            "username": "Keroia",
            "score": 59
        },
        {
            "username": "RawrMommy",
            "score": 59
        },
        {
            "username": "xDun58",
            "score": 59
        },
        {
            "username": "Madam_Donut",
            "score": 59
        },
        {
            "username": "Kytato",
            "score": 59
        },
        {
            "username": "NodSpurdo",
            "score": 59
        },
        {
            "username": "StabBee",
            "score": 59
        },
        {
            "username": "arj",
            "score": 58
        },
        {
            "username": "anuei",
            "score": 58
        },
        {
            "username": "_EduardoLorite_",
            "score": 58
        },
        {
            "username": "AwesomeGamerMG",
            "score": 58
        },
        {
            "username": "Mcprocosmic",
            "score": 58
        },
        {
            "username": "Sarzh",
            "score": 58
        },
        {
            "username": "rjcj",
            "score": 58
        },
        {
            "username": "Hadokoi",
            "score": 58
        },
        {
            "username": "xsara3x",
            "score": 58
        },
        {
            "username": "aliensushi",
            "score": 58
        },
        {
            "username": "Zombiez",
            "score": 58
        },
        {
            "username": "Loiyn",
            "score": 58
        },
        {
            "username": "Tedsworth",
            "score": 58
        },
        {
            "username": "SoulBreaker2002",
            "score": 58
        },
        {
            "username": "586",
            "score": 58
        },
        {
            "username": "TheBoshQueen",
            "score": 58
        },
        {
            "username": "BriZmo",
            "score": 58
        },
        {
            "username": "ButtKillsYou",
            "score": 58
        },
        {
            "username": "Doncraft11",
            "score": 58
        },
        {
            "username": "ILoveLucas",
            "score": 58
        },
        {
            "username": "Victr",
            "score": 57
        },
        {
            "username": "p1h2i3l4i5p6p7",
            "score": 57
        },
        {
            "username": "TW_Roy_PVP",
            "score": 57
        },
        {
            "username": "lil_real",
            "score": 57
        },
        {
            "username": "alessiogori",
            "score": 57
        },
        {
            "username": "OmerHD",
            "score": 57
        },
        {
            "username": "WilfulVoice2294",
            "score": 57
        },
        {
            "username": "ChickMcNug",
            "score": 57
        },
        {
            "username": "alxanban",
            "score": 57
        },
        {
            "username": "Jonathanboss26",
            "score": 57
        },
        {
            "username": "Alexsonicspeed",
            "score": 57
        },
        {
            "username": "Elihoot",
            "score": 57
        },
        {
            "username": "actuallyDONKEY",
            "score": 57
        },
        {
            "username": "Zaku47",
            "score": 57
        },
        {
            "username": "VacePro",
            "score": 57
        },
        {
            "username": "xkllr0928x",
            "score": 57
        },
        {
            "username": "Thundorus",
            "score": 57
        },
        {
            "username": "ImLeftClicking",
            "score": 57
        },
        {
            "username": "Gaston0418",
            "score": 57
        },
        {
            "username": "Sheeepeee",
            "score": 57
        },
        {
            "username": "FlpDaMattress",
            "score": 57
        },
        {
            "username": "Miichaela",
            "score": 57
        },
        {
            "username": "DollarStoreWiFi",
            "score": 57
        },
        {
            "username": "squid242",
            "score": 57
        },
        {
            "username": "CptCabbage",
            "score": 57
        },
        {
            "username": "Strander24",
            "score": 57
        },
        {
            "username": "RedLarson",
            "score": 57
        },
        {
            "username": "NewSix_tw1",
            "score": 56
        },
        {
            "username": "Andreej",
            "score": 56
        },
        {
            "username": "McCataclysm",
            "score": 56
        },
        {
            "username": "Slowpke",
            "score": 56
        },
        {
            "username": "zLina",
            "score": 56
        },
        {
            "username": "Sozeash",
            "score": 56
        },
        {
            "username": "phft",
            "score": 56
        },
        {
            "username": "IRelyOnGamesense",
            "score": 56
        },
        {
            "username": "HawkenMC",
            "score": 56
        },
        {
            "username": "bbyluvs",
            "score": 56
        },
        {
            "username": "TheClassyIdiot",
            "score": 56
        },
        {
            "username": "ShesPerfect",
            "score": 56
        },
        {
            "username": "Zycie",
            "score": 56
        },
        {
            "username": "MineBrasil_",
            "score": 56
        },
        {
            "username": "Demonicus",
            "score": 56
        },
        {
            "username": "_______l________",
            "score": 56
        },
        {
            "username": "_Bedo_",
            "score": 56
        },
        {
            "username": "Ovalard",
            "score": 56
        },
        {
            "username": "iAvocado",
            "score": 55
        },
        {
            "username": "_Krompirko_",
            "score": 55
        },
        {
            "username": "Swanke",
            "score": 55
        },
        {
            "username": "peacekeep",
            "score": 55
        },
        {
            "username": "Evileus",
            "score": 55
        },
        {
            "username": "Idut",
            "score": 55
        },
        {
            "username": "DaOnlyMunchy",
            "score": 55
        },
        {
            "username": "AidedDeer",
            "score": 55
        },
        {
            "username": "awesome_blockman",
            "score": 55
        },
        {
            "username": "iDeadmau5",
            "score": 55
        },
        {
            "username": "4KDNA",
            "score": 55
        },
        {
            "username": "kattea",
            "score": 55
        },
        {
            "username": "Patrykus86",
            "score": 55
        },
        {
            "username": "TaySaucePan",
            "score": 55
        },
        {
            "username": "leemir8992",
            "score": 55
        },
        {
            "username": "Swuge",
            "score": 55
        },
        {
            "username": "THIGHHEADCRUSH",
            "score": 55
        },
        {
            "username": "JerBoiiFire",
            "score": 55
        },
        {
            "username": "explorerman22",
            "score": 55
        },
        {
            "username": "candypompomFAN",
            "score": 55
        },
        {
            "username": "ExertKarma",
            "score": 55
        },
        {
            "username": "Vaux_Echo",
            "score": 55
        },
        {
            "username": "Curnow",
            "score": 55
        },
        {
            "username": "JacksonGrim",
            "score": 55
        },
        {
            "username": "TheelVadamee",
            "score": 55
        },
        {
            "username": "oemily",
            "score": 55
        },
        {
            "username": "Collpry",
            "score": 55
        },
        {
            "username": "Raydnn",
            "score": 55
        },
        {
            "username": "Alphaflower16",
            "score": 55
        },
        {
            "username": "XanXan",
            "score": 55
        },
        {
            "username": "Allykaty",
            "score": 55
        },
        {
            "username": "4cer",
            "score": 55
        },
        {
            "username": "1c2",
            "score": 54
        },
        {
            "username": "kim_crazy",
            "score": 54
        },
        {
            "username": "Speeeding",
            "score": 54
        },
        {
            "username": "darktimes15",
            "score": 54
        },
        {
            "username": "Creepering_Along",
            "score": 54
        },
        {
            "username": "GrayDrakon",
            "score": 54
        },
        {
            "username": "DarkSaberNight",
            "score": 54
        },
        {
            "username": "SpiritedArren",
            "score": 54
        },
        {
            "username": "beastflipper",
            "score": 54
        },
        {
            "username": "Aldooo",
            "score": 54
        },
        {
            "username": "EATMYPICKLE96",
            "score": 54
        },
        {
            "username": "Axerith",
            "score": 54
        },
        {
            "username": "AntheronMC",
            "score": 54
        },
        {
            "username": "arsh350",
            "score": 54
        },
        {
            "username": "MelkorADeceiver",
            "score": 54
        },
        {
            "username": "Alexiem",
            "score": 54
        },
        {
            "username": "Tyde",
            "score": 54
        },
        {
            "username": "Teslq",
            "score": 54
        },
        {
            "username": "TheJohan_",
            "score": 54
        },
        {
            "username": "Ninjaname",
            "score": 54
        },
        {
            "username": "PigNuggett",
            "score": 54
        },
        {
            "username": "msyb_b3n",
            "score": 54
        },
        {
            "username": "Duntaine",
            "score": 54
        },
        {
            "username": "Gremy",
            "score": 54
        },
        {
            "username": "PepitoBarajas",
            "score": 54
        },
        {
            "username": "SadGoon",
            "score": 54
        },
        {
            "username": "Studz_McGee",
            "score": 54
        },
        {
            "username": "Zepper2004",
            "score": 53
        },
        {
            "username": "oWrqth",
            "score": 53
        },
        {
            "username": "Champiez",
            "score": 53
        },
        {
            "username": "Mind_Buster202",
            "score": 53
        },
        {
            "username": "Heleye",
            "score": 53
        },
        {
            "username": "abram133",
            "score": 53
        },
        {
            "username": "MomentoMori",
            "score": 53
        },
        {
            "username": "_Arch",
            "score": 53
        },
        {
            "username": "Paolo_222YT",
            "score": 53
        },
        {
            "username": "StankyLegson",
            "score": 53
        },
        {
            "username": "YungGlaze",
            "score": 53
        },
        {
            "username": "WildBearDuck",
            "score": 53
        },
        {
            "username": "eusouvoce",
            "score": 53
        },
        {
            "username": "Viners",
            "score": 53
        },
        {
            "username": "ZachPoops_lolxd",
            "score": 53
        },
        {
            "username": "FLWME",
            "score": 53
        },
        {
            "username": "ghjj34",
            "score": 53
        },
        {
            "username": "Looniitick",
            "score": 53
        },
        {
            "username": "Kolohegirl",
            "score": 53
        },
        {
            "username": "xX_Shrek_Xx",
            "score": 53
        },
        {
            "username": "Orphanated",
            "score": 53
        },
        {
            "username": "great_guy2",
            "score": 53
        },
        {
            "username": "Zesshi_Zetsumei",
            "score": 53
        },
        {
            "username": "CompleteCrab",
            "score": 53
        },
        {
            "username": "Odrmrr",
            "score": 53
        },
        {
            "username": "TheFancyCanadian",
            "score": 53
        },
        {
            "username": "DMRH",
            "score": 53
        },
        {
            "username": "Adstrum",
            "score": 53
        },
        {
            "username": "Dylllon",
            "score": 52
        },
        {
            "username": "niilo22xp",
            "score": 52
        },
        {
            "username": "SleeepyDuck",
            "score": 52
        },
        {
            "username": "laurj",
            "score": 52
        },
        {
            "username": "iNotThinkOfaName",
            "score": 52
        },
        {
            "username": "Chknugitz916",
            "score": 52
        },
        {
            "username": "baevillier",
            "score": 52
        },
        {
            "username": "ScarsFromEnder",
            "score": 52
        },
        {
            "username": "Verdesouro",
            "score": 52
        },
        {
            "username": "Jorsair",
            "score": 52
        },
        {
            "username": "Parli9",
            "score": 52
        },
        {
            "username": "Pizzazilla",
            "score": 52
        },
        {
            "username": "miasmalism",
            "score": 52
        },
        {
            "username": "PokeCraftFTW",
            "score": 52
        },
        {
            "username": "EnderKreep3",
            "score": 52
        },
        {
            "username": "Notrom",
            "score": 52
        },
        {
            "username": "GymMember",
            "score": 52
        },
        {
            "username": "roeethebuilder",
            "score": 52
        },
        {
            "username": "TheCookieHunterz",
            "score": 52
        },
        {
            "username": "FrogSenpai13",
            "score": 52
        },
        {
            "username": "Sketching_Cookie",
            "score": 52
        },
        {
            "username": "quteLexie",
            "score": 52
        },
        {
            "username": "Jarias",
            "score": 52
        },
        {
            "username": "IGLOOGHOST",
            "score": 52
        },
        {
            "username": "100Scar",
            "score": 52
        },
        {
            "username": "ShyStone",
            "score": 52
        },
        {
            "username": "jak_atak116",
            "score": 52
        },
        {
            "username": "Saiges",
            "score": 52
        },
        {
            "username": "Hpi",
            "score": 52
        },
        {
            "username": "Cance",
            "score": 51
        },
        {
            "username": "easydunkin",
            "score": 51
        },
        {
            "username": "SGU23",
            "score": 51
        },
        {
            "username": "kafermanky",
            "score": 51
        },
        {
            "username": "Sir_Stewart",
            "score": 51
        },
        {
            "username": "Liezuli",
            "score": 51
        },
        {
            "username": "CliqueCat",
            "score": 51
        },
        {
            "username": "HerbertTheDuck",
            "score": 51
        },
        {
            "username": "TwoChimneysInOne",
            "score": 51
        },
        {
            "username": "Monkeyonapig",
            "score": 51
        },
        {
            "username": "AliceKingsley_",
            "score": 51
        },
        {
            "username": "Th3_Impersonator",
            "score": 51
        },
        {
            "username": "Gregoriosa",
            "score": 51
        },
        {
            "username": "LittleGoodMan",
            "score": 51
        },
        {
            "username": "Tyxuder",
            "score": 51
        },
        {
            "username": "DietSugar",
            "score": 51
        },
        {
            "username": "Cretinize",
            "score": 51
        },
        {
            "username": "HyC_Podemarco",
            "score": 51
        },
        {
            "username": "SirBannedAlot",
            "score": 51
        },
        {
            "username": "LordSasori",
            "score": 51
        },
        {
            "username": "Liqhten",
            "score": 51
        },
        {
            "username": "Nyes",
            "score": 51
        },
        {
            "username": "BUGATTl",
            "score": 51
        },
        {
            "username": "kayped",
            "score": 51
        },
        {
            "username": "Milkshakesss",
            "score": 51
        },
        {
            "username": "xLeopard",
            "score": 51
        },
        {
            "username": "Nalu",
            "score": 51
        },
        {
            "username": "ItzCqnadian",
            "score": 51
        },
        {
            "username": "maxibob12_dow",
            "score": 51
        },
        {
            "username": "bundyskid",
            "score": 51
        },
        {
            "username": "ItzHelder",
            "score": 50
        },
        {
            "username": "gayie",
            "score": 50
        },
        {
            "username": "Clapts",
            "score": 50
        },
        {
            "username": "_EliteAuthority",
            "score": 50
        },
        {
            "username": "21madlad",
            "score": 50
        },
        {
            "username": "EisernerKanzler_",
            "score": 50
        },
        {
            "username": "zMeliodas__",
            "score": 50
        },
        {
            "username": "Apollo4K",
            "score": 50
        },
        {
            "username": "Doppelganger10",
            "score": 50
        },
        {
            "username": "Liaorewai",
            "score": 50
        },
        {
            "username": "SeymourSimmons",
            "score": 50
        },
        {
            "username": "Elmar0",
            "score": 50
        },
        {
            "username": "CrocodileA",
            "score": 50
        },
        {
            "username": "Guineu_",
            "score": 50
        },
        {
            "username": "rhennigan",
            "score": 50
        },
        {
            "username": "Unique_Guy",
            "score": 50
        },
        {
            "username": "filijewsian",
            "score": 50
        },
        {
            "username": "ExpectedXV",
            "score": 50
        },
        {
            "username": "GamerCatgirl_UwU",
            "score": 50
        },
        {
            "username": "adiskill",
            "score": 50
        },
        {
            "username": "viktorv9",
            "score": 50
        },
        {
            "username": "YumKandie",
            "score": 50
        },
        {
            "username": "YNV",
            "score": 50
        },
        {
            "username": "Wuelis",
            "score": 50
        },
        {
            "username": "Leandro",
            "score": 50
        },
        {
            "username": "Chilledstep",
            "score": 50
        },
        {
            "username": "bionicle8j",
            "score": 50
        },
        {
            "username": "MrPhoenix",
            "score": 50
        },
        {
            "username": "NeroXever",
            "score": 50
        },
        {
            "username": "Snowy121",
            "score": 50
        },
        {
            "username": "Awakrus",
            "score": 50
        },
        {
            "username": "GottaGoFasta",
            "score": 50
        },
        {
            "username": "AndrewC7",
            "score": 50
        },
        {
            "username": "BenJC4",
            "score": 50
        },
        {
            "username": "iKade",
            "score": 49
        },
        {
            "username": "Divit",
            "score": 49
        },
        {
            "username": "ImagineSweating",
            "score": 49
        },
        {
            "username": "Nasaa",
            "score": 49
        },
        {
            "username": "SirDeliciousD",
            "score": 49
        },
        {
            "username": "Tomi2003",
            "score": 49
        },
        {
            "username": "SquishyDog77",
            "score": 49
        },
        {
            "username": "MrFoxtastic",
            "score": 49
        },
        {
            "username": "Talkhouse",
            "score": 49
        },
        {
            "username": "FatFood",
            "score": 49
        },
        {
            "username": "gayfully",
            "score": 49
        },
        {
            "username": "wtfcolin",
            "score": 49
        },
        {
            "username": "josortiz2",
            "score": 49
        },
        {
            "username": "BLONDSPOCK",
            "score": 49
        },
        {
            "username": "BIGROCK863",
            "score": 49
        },
        {
            "username": "rorey",
            "score": 49
        },
        {
            "username": "SeeGamerHD",
            "score": 49
        },
        {
            "username": "Ashton5811",
            "score": 49
        },
        {
            "username": "NeverGame",
            "score": 49
        },
        {
            "username": "_Tetris_",
            "score": 49
        },
        {
            "username": "Taal",
            "score": 49
        },
        {
            "username": "Faelynxia",
            "score": 49
        },
        {
            "username": "TopTen",
            "score": 49
        },
        {
            "username": "SilverDT",
            "score": 49
        },
        {
            "username": "JITTEH",
            "score": 49
        },
        {
            "username": "bunnymarvel",
            "score": 49
        },
        {
            "username": "josem123jr",
            "score": 49
        },
        {
            "username": "joserobjr",
            "score": 49
        },
        {
            "username": "Eroil",
            "score": 49
        },
        {
            "username": "unpinned",
            "score": 49
        },
        {
            "username": "Jrolles",
            "score": 49
        },
        {
            "username": "ryonthesav",
            "score": 49
        },
        {
            "username": "Asunares",
            "score": 49
        },
        {
            "username": "duhbz",
            "score": 48
        },
        {
            "username": "wolfer04",
            "score": 48
        },
        {
            "username": "Dragone100",
            "score": 48
        },
        {
            "username": "cwuties",
            "score": 48
        },
        {
            "username": "usaq",
            "score": 48
        },
        {
            "username": "Demoniica_",
            "score": 48
        },
        {
            "username": "itsrenewal",
            "score": 48
        },
        {
            "username": "Kyogre",
            "score": 48
        },
        {
            "username": "chromebook_god",
            "score": 48
        },
        {
            "username": "aHidden",
            "score": 48
        },
        {
            "username": "CiumciugaXD69",
            "score": 48
        },
        {
            "username": "_Yune_",
            "score": 48
        },
        {
            "username": "EarlGreyLatte",
            "score": 48
        },
        {
            "username": "Khuzzy",
            "score": 48
        },
        {
            "username": "Inverts",
            "score": 48
        },
        {
            "username": "morningblackwood",
            "score": 48
        },
        {
            "username": "mathwhizkid",
            "score": 48
        },
        {
            "username": "Jqrrett",
            "score": 48
        },
        {
            "username": "Piplupluv",
            "score": 48
        },
        {
            "username": "Lins__",
            "score": 48
        },
        {
            "username": "CartierBourne",
            "score": 48
        },
        {
            "username": "katsuko_",
            "score": 48
        },
        {
            "username": "FailGiraffes",
            "score": 48
        },
        {
            "username": "Starclone",
            "score": 48
        },
        {
            "username": "Ktrini",
            "score": 48
        },
        {
            "username": "BaeCan",
            "score": 48
        },
        {
            "username": "GLUTENFREEJELLY",
            "score": 48
        },
        {
            "username": "Shababa",
            "score": 48
        },
        {
            "username": "chadplays",
            "score": 48
        },
        {
            "username": "Callandor",
            "score": 48
        },
        {
            "username": "Twilazs",
            "score": 48
        },
        {
            "username": "PinHeadCade",
            "score": 48
        },
        {
            "username": "Theminerscode",
            "score": 48
        },
        {
            "username": "SilverSky009",
            "score": 48
        },
        {
            "username": "xGriz",
            "score": 48
        },
        {
            "username": "OverscorePlayZ",
            "score": 48
        },
        {
            "username": "Dudangel",
            "score": 48
        },
        {
            "username": "Arrison",
            "score": 48
        },
        {
            "username": "Isabaaat",
            "score": 48
        },
        {
            "username": "TobiGoro",
            "score": 48
        },
        {
            "username": "bobert2013",
            "score": 47
        },
        {
            "username": "MineEcho",
            "score": 47
        },
        {
            "username": "_backwqrds_",
            "score": 47
        },
        {
            "username": "EndlessSword",
            "score": 47
        },
        {
            "username": "RuTwo",
            "score": 47
        },
        {
            "username": "Wethaze",
            "score": 47
        },
        {
            "username": "Damysq_",
            "score": 47
        },
        {
            "username": "Scott970",
            "score": 47
        },
        {
            "username": "02_10_04",
            "score": 47
        },
        {
            "username": "BurningMiner_YT",
            "score": 47
        },
        {
            "username": "FoxyliciousBoi15",
            "score": 47
        },
        {
            "username": "Majuak",
            "score": 47
        },
        {
            "username": "quangiepoo",
            "score": 47
        },
        {
            "username": "ihysvm",
            "score": 47
        },
        {
            "username": "0akkung",
            "score": 47
        },
        {
            "username": "ADuckWithATopHat",
            "score": 47
        },
        {
            "username": "Zeccen",
            "score": 47
        },
        {
            "username": "MaxKeenti",
            "score": 47
        },
        {
            "username": "Buuurds",
            "score": 47
        },
        {
            "username": "tiff",
            "score": 47
        },
        {
            "username": "Blaegogue",
            "score": 47
        },
        {
            "username": "GiorgioBrux",
            "score": 47
        },
        {
            "username": "Shabootiquiqui_",
            "score": 47
        },
        {
            "username": "7XCOLE",
            "score": 47
        },
        {
            "username": "badnewsnick",
            "score": 47
        },
        {
            "username": "Dyxter",
            "score": 47
        },
        {
            "username": "TheRadPaulo",
            "score": 47
        },
        {
            "username": "ThyIlluminati3",
            "score": 47
        },
        {
            "username": "NubLyfe",
            "score": 47
        },
        {
            "username": "Instant_Max",
            "score": 47
        },
        {
            "username": "0lko",
            "score": 47
        },
        {
            "username": "Ambrotas",
            "score": 47
        },
        {
            "username": "mzddy",
            "score": 47
        },
        {
            "username": "tuckyouteeners",
            "score": 47
        },
        {
            "username": "SOULHARDY",
            "score": 47
        },
        {
            "username": "DragonXiao",
            "score": 47
        },
        {
            "username": "Sehtii",
            "score": 47
        },
        {
            "username": "PretzelPresley",
            "score": 47
        },
        {
            "username": "Athena404",
            "score": 47
        },
        {
            "username": "StrawberryTrap",
            "score": 47
        },
        {
            "username": "Bonemare",
            "score": 47
        },
        {
            "username": "m4ybe_m3mes",
            "score": 47
        },
        {
            "username": "MonzMain",
            "score": 47
        },
        {
            "username": "Aestheticest",
            "score": 47
        },
        {
            "username": "Fluffy_Enderman",
            "score": 47
        },
        {
            "username": "CODExADRENALINE",
            "score": 47
        },
        {
            "username": "Fuzzbearplush",
            "score": 46
        },
        {
            "username": "HazAdarous",
            "score": 46
        },
        {
            "username": "DiamondTurtle510",
            "score": 46
        },
        {
            "username": "TheWubDub",
            "score": 46
        },
        {
            "username": "Timolino456",
            "score": 46
        },
        {
            "username": "XxShadowstalkerx",
            "score": 46
        },
        {
            "username": "rubzn",
            "score": 46
        },
        {
            "username": "M3chuCantMelee",
            "score": 46
        },
        {
            "username": "ButUrMyStepMom",
            "score": 46
        },
        {
            "username": "huux",
            "score": 46
        },
        {
            "username": "Mahxs",
            "score": 46
        },
        {
            "username": "lengthyspaceworm",
            "score": 46
        },
        {
            "username": "Mami_Tomo3",
            "score": 46
        },
        {
            "username": "Mangrove",
            "score": 46
        },
        {
            "username": "Pinpointed",
            "score": 46
        },
        {
            "username": "notch_LP",
            "score": 46
        },
        {
            "username": "klassisk",
            "score": 46
        },
        {
            "username": "Crystalcracker",
            "score": 46
        },
        {
            "username": "dorabora",
            "score": 46
        },
        {
            "username": "notfor2",
            "score": 46
        },
        {
            "username": "Sneasler",
            "score": 46
        },
        {
            "username": "Landay",
            "score": 46
        },
        {
            "username": "michaelwang2001",
            "score": 46
        },
        {
            "username": "Xbe",
            "score": 46
        },
        {
            "username": "3100east",
            "score": 46
        },
        {
            "username": "6xU7Strafez",
            "score": 46
        },
        {
            "username": "winedNdinedN69nd",
            "score": 46
        },
        {
            "username": "SnowZumi",
            "score": 46
        },
        {
            "username": "Tjyrker",
            "score": 46
        },
        {
            "username": "Flurn",
            "score": 46
        },
        {
            "username": "Banoop",
            "score": 46
        },
        {
            "username": "Madixly",
            "score": 46
        },
        {
            "username": "Dvsa0614",
            "score": 46
        },
        {
            "username": "Jop_man",
            "score": 46
        },
        {
            "username": "denistreulea",
            "score": 46
        },
        {
            "username": "Shadyyyyyyyyyyyy",
            "score": 46
        },
        {
            "username": "gavin1214",
            "score": 46
        },
        {
            "username": "mutantdevle",
            "score": 46
        },
        {
            "username": "otokohaookami",
            "score": 46
        },
        {
            "username": "KingKwak",
            "score": 46
        },
        {
            "username": "MiningMinecraft",
            "score": 46
        },
        {
            "username": "Adundance__",
            "score": 46
        },
        {
            "username": "Syns",
            "score": 46
        },
        {
            "username": "collincaptain",
            "score": 46
        },
        {
            "username": "Frenchcore621",
            "score": 46
        },
        {
            "username": "MPPrint",
            "score": 45
        },
        {
            "username": "_marc1nekkk",
            "score": 45
        },
        {
            "username": "Remkun",
            "score": 45
        },
        {
            "username": "DynamicHD",
            "score": 45
        },
        {
            "username": "Dragonmaster92",
            "score": 45
        },
        {
            "username": "Starrccookie",
            "score": 45
        },
        {
            "username": "Lordofward",
            "score": 45
        },
        {
            "username": "TyphlosionGamer",
            "score": 45
        },
        {
            "username": "drut",
            "score": 45
        },
        {
            "username": "bluenugget25",
            "score": 45
        },
        {
            "username": "SenorPenguin",
            "score": 45
        },
        {
            "username": "K0WL",
            "score": 45
        },
        {
            "username": "3good5mineplex",
            "score": 45
        },
        {
            "username": "sqmqrqndqmgqy",
            "score": 45
        },
        {
            "username": "Flobond23",
            "score": 45
        },
        {
            "username": "stoopid12",
            "score": 45
        },
        {
            "username": "Wolverine434",
            "score": 45
        },
        {
            "username": "Mini4571",
            "score": 45
        },
        {
            "username": "razzitazzi",
            "score": 45
        },
        {
            "username": "Clockstopper12",
            "score": 45
        },
        {
            "username": "Chikken_",
            "score": 45
        },
        {
            "username": "MIPN11",
            "score": 45
        },
        {
            "username": "thesheepchief",
            "score": 45
        },
        {
            "username": "xsloby",
            "score": 45
        },
        {
            "username": "TheKsuFoket",
            "score": 45
        },
        {
            "username": "PhoenixSummoning",
            "score": 45
        },
        {
            "username": "99LightMan",
            "score": 45
        },
        {
            "username": "Autumnfound",
            "score": 45
        },
        {
            "username": "Rocca_V",
            "score": 45
        },
        {
            "username": "NogerFlesh",
            "score": 45
        },
        {
            "username": "TimeHelix",
            "score": 45
        },
        {
            "username": "Warag",
            "score": 45
        },
        {
            "username": "KingOfWizards",
            "score": 45
        },
        {
            "username": "chqnse",
            "score": 45
        },
        {
            "username": "Satoriji",
            "score": 45
        },
        {
            "username": "SoulTheBunny",
            "score": 45
        },
        {
            "username": "Max_The_Bunnie",
            "score": 45
        },
        {
            "username": "Tommygun3000",
            "score": 45
        },
        {
            "username": "AngryGrandma101",
            "score": 45
        },
        {
            "username": "Unova",
            "score": 45
        },
        {
            "username": "Haruki1703",
            "score": 45
        },
        {
            "username": "Kevstea",
            "score": 45
        },
        {
            "username": "GooberDayz",
            "score": 45
        },
        {
            "username": "FireboltJohn",
            "score": 45
        },
        {
            "username": "ThePumpkinIKing",
            "score": 45
        },
        {
            "username": "OCplays",
            "score": 45
        },
        {
            "username": "DarkHunter_IV",
            "score": 45
        },
        {
            "username": "korniDE",
            "score": 45
        },
        {
            "username": "xInnocence",
            "score": 45
        },
        {
            "username": "GamingDaily",
            "score": 45
        },
        {
            "username": "Treesan",
            "score": 45
        },
        {
            "username": "_TheMax_331",
            "score": 45
        },
        {
            "username": "billciipher",
            "score": 45
        },
        {
            "username": "HydrantDude",
            "score": 45
        },
        {
            "username": "huss__",
            "score": 44
        },
        {
            "username": "BillLmao",
            "score": 44
        },
        {
            "username": "Cadent313",
            "score": 44
        },
        {
            "username": "SecretlyRyan",
            "score": 44
        },
        {
            "username": "Mushroomman733",
            "score": 44
        },
        {
            "username": "T5v",
            "score": 44
        },
        {
            "username": "KnowBoutShmokey",
            "score": 44
        },
        {
            "username": "5i3",
            "score": 44
        },
        {
            "username": "ueku",
            "score": 44
        },
        {
            "username": "DreadLord898",
            "score": 44
        },
        {
            "username": "K1TEGOD",
            "score": 44
        },
        {
            "username": "Marvinix",
            "score": 44
        },
        {
            "username": "DeluxFTW",
            "score": 44
        },
        {
            "username": "felemiah",
            "score": 44
        },
        {
            "username": "zCosmosZ",
            "score": 44
        },
        {
            "username": "_quiz",
            "score": 44
        },
        {
            "username": "Dr_Veemo",
            "score": 44
        },
        {
            "username": "Abstractted",
            "score": 44
        },
        {
            "username": "MJtheminer",
            "score": 44
        },
        {
            "username": "secretspy1234",
            "score": 44
        },
        {
            "username": "BMLGinger",
            "score": 44
        },
        {
            "username": "Pumpkin3_14",
            "score": 44
        },
        {
            "username": "1mb_ram",
            "score": 44
        },
        {
            "username": "SemperFive",
            "score": 44
        },
        {
            "username": "TheFirstLaw",
            "score": 44
        },
        {
            "username": "Thing__",
            "score": 44
        },
        {
            "username": "1BlockUp",
            "score": 44
        },
        {
            "username": "_PanYoutuber_",
            "score": 44
        },
        {
            "username": "Yancheef",
            "score": 44
        },
        {
            "username": "GGamerFTW",
            "score": 44
        },
        {
            "username": "Glitz",
            "score": 44
        },
        {
            "username": "CDGT11",
            "score": 44
        },
        {
            "username": "MattteaMischief",
            "score": 44
        },
        {
            "username": "ums",
            "score": 44
        },
        {
            "username": "Benjanas",
            "score": 44
        },
        {
            "username": "Xak",
            "score": 44
        }
    ]
}